sqlproxy/__init__.py
sqlproxy/cli.py
sqlproxy-0.3.dist-info/METADATA
sqlproxy-0.3.dist-info/WHEEL
sqlproxy-0.3.dist-info/entry_points.txt
sqlproxy-0.3.dist-info/top_level.txt
sqlproxy-0.3.dist-info/RECORD
