Metadata-Version: 2.4
Name: sqlproxy
Version: 0.3
Summary: A simple proxy automation tool using Burp Suite for login testing
Author: Baskar
Classifier: Programming Language :: Python :: 3
Classifier: Operating System :: Microsoft :: Windows
Requires-Python: >=3.6
Requires-Dist: requests
Requires-Dist: keyboard
Requires-Dist: urllib3
Dynamic: author
Dynamic: classifier
Dynamic: requires-dist
Dynamic: requires-python
Dynamic: summary
